transkribus_metagrapho_api/__init__.py
transkribus_metagrapho_api/__main__.py
transkribus_metagrapho_api/api.py
transkribus_metagrapho_api/app.py
transkribus_metagrapho_api/py.typed
transkribus_metagrapho_api-0.2.0.dist-info/licenses/LICENSE
transkribus_metagrapho_api-0.2.0.dist-info/METADATA
transkribus_metagrapho_api-0.2.0.dist-info/WHEEL
transkribus_metagrapho_api-0.2.0.dist-info/top_level.txt
transkribus_metagrapho_api-0.2.0.dist-info/RECORD
