Metadata-Version: 2.4
Name: transkribus_metagrapho_api
Version: 0.2.0
Summary: Transkribus Metagrapho API Client.
Author-email: "J. Nathanael Philipp" <nathanael@philipp.land>
License: GPLv3+
Project-URL: Homepage, https://github.com/jnphilipp/transkribus_metagrapho_api
Project-URL: Bug Tracker, http://github.com/jnphilipp/transkribus_metagrapho_api/issues
Keywords: transkribus,api
Classifier: Development Status :: 5 - Production/Stable
Classifier: Environment :: Web Environment
Classifier: Intended Audience :: Developers
Classifier: License :: OSI Approved :: GNU General Public License v3 or later (GPLv3+)
Classifier: Operating System :: OS Independent
Classifier: Programming Language :: Python
Classifier: Programming Language :: Python :: 3.10
Classifier: Programming Language :: Python :: 3.11
Classifier: Programming Language :: Python :: 3.12
Classifier: Programming Language :: Python :: 3.13
Classifier: Topic :: Software Development :: Libraries :: Python Modules
Requires-Python: >=3.10
License-File: LICENSE
Requires-Dist: Pillow~=11.1.0
Requires-Dist: requests~=2.32.0
Dynamic: license-file
